{
    "name": "Derrick Estrada",
    "age": 53,
    "address": {
        "street": "King Tunnel",
        "city": "Lake Briantown",
        "state": "Rhode Island",
        "zip": "22239"
    },
    "contact": {
        "phone": "2362209712",
        "servicePhone": "800802798"
    },
    "birthday": "1972-06-01",
    "ip": "143.205.144.188",
    "foo": "bar",
    "profile": {
        "about": "Present new guy seek dark. Same answer size.\nDinner whose election radio receive center administration. Information security employee toward. Month next perhaps impact adult.",
        "bio": "Compare up feel rule. Person artist course understand everything American. Continue pick arrive federal simply thank."
    },
    "apiKey": "1108277933fbc48b155f2419f625a5cccbc873b8eb739dcc08995bb147dc3a12",
    "currency": [
        "VEF",
        "Venezuelan bolívar"
    ]
}